onlineProdebnet/CompensationNet.py
onlineProdebnet/DefocusNet.py
onlineProdebnet/LuminanceNet.py
onlineProdebnet/__init__.py
onlineProdebnet/__version__.py
onlineProdebnet-0.0.1.dist-info/LICENSE.txt
onlineProdebnet-0.0.1.dist-info/METADATA
onlineProdebnet-0.0.1.dist-info/WHEEL
onlineProdebnet-0.0.1.dist-info/top_level.txt
onlineProdebnet-0.0.1.dist-info/RECORD
