Metadata-Version: 2.1
Name: onlineProdebnet
Version: 0.0.1
Summary: implementaion of IEEE tvcg paper: Online Projector Deblurring Using a Convolutional Neural Network
Home-page: https://github.com/kagechan5/Online-Projector-Deblurring-Using-a-Convolutional-Neural-Network
Author: kagechan5
License: UNKNOWN
Platform: UNKNOWN
Requires-Python: >=3.7
License-File: LICENSE.txt
Requires-Dist: Keras (==2.4.0)
Requires-Dist: opencv-python (==3.4.2.16)
Requires-Dist: tensorflow (==2.3.1)
Requires-Dist: tensorflow-probability (==0.11.0)
